{
	"archive" : {},
	"artifacts" : 
	[
		{
			"path" : "build/pathkit.lib"
		}
	],
	"backtrace" : 3,
	"backtraceGraph" : 
	{
		"commands" : 
		[
			"add_library",
			"include",
			"set_target_properties",
			"set_property",
			"include_directories"
		],
		"files" : 
		[
			"C:/skia/out/config/CMakeLists.ext",
			"C:/skia/out/config/CMakeLists.txt"
		],
		"nodes" : 
		[
			{
				"file" : 1
			},
			{
				"command" : 1,
				"file" : 1,
				"line" : 13,
				"parent" : 0
			},
			{
				"file" : 0,
				"parent" : 1
			},
			{
				"command" : 0,
				"file" : 0,
				"line" : 3084,
				"parent" : 2
			},
			{
				"command" : 2,
				"file" : 0,
				"line" : 3093,
				"parent" : 2
			},
			{
				"command" : 3,
				"file" : 0,
				"line" : 3086,
				"parent" : 2
			},
			{
				"command" : 4,
				"file" : 1,
				"line" : 14,
				"parent" : 0
			}
		]
	},
	"compileGroups" : 
	[
		{
			"compileCommandFragments" : 
			[
				{
					"fragment" : "/DWIN32 /D_WINDOWS /EHsc /Ob0 /Od /RTC1 -MDd -Zi"
				},
				{
					"fragment" : "/wd5030 /wd5051 /bigobj /utf-8 /Z7 /W3 /wd4244 /wd4267 /wd4800 /wd4291 /wd4251 /wd4275 /wd5041 /std:c++17 /GR- "
				}
			],
			"defines" : 
			[
				{
					"backtrace" : 4,
					"define" : "GR_TEST_UTILS=1"
				},
				{
					"backtrace" : 4,
					"define" : "NOMINMAX"
				},
				{
					"backtrace" : 4,
					"define" : "SKIA_IMPLEMENTATION=1"
				},
				{
					"backtrace" : 4,
					"define" : "SK_ALLOW_STATIC_GLOBAL_INITIALIZERS=1"
				},
				{
					"backtrace" : 4,
					"define" : "SK_ENABLE_PRECOMPILE"
				},
				{
					"backtrace" : 4,
					"define" : "SK_GAMMA_APPLY_TO_A8"
				},
				{
					"backtrace" : 4,
					"define" : "SK_GANESH"
				},
				{
					"backtrace" : 4,
					"define" : "WIN32_LEAN_AND_MEAN"
				},
				{
					"backtrace" : 4,
					"define" : "_CRT_SECURE_NO_WARNINGS"
				},
				{
					"backtrace" : 4,
					"define" : "_HAS_EXCEPTIONS=0"
				}
			],
			"includes" : 
			[
				{
					"backtrace" : 5,
					"path" : "C:/Program Files/Microsoft Visual Studio/2022/Community/VC/Tools/MSVC/14.36.32532/include"
				},
				{
					"backtrace" : 5,
					"path" : "C:/Program Files (x86)/Windows Kits/10/Include/10.0.22000.0/shared"
				},
				{
					"backtrace" : 5,
					"path" : "C:/Program Files (x86)/Windows Kits/10/Include/10.0.22000.0/ucrt"
				},
				{
					"backtrace" : 5,
					"path" : "C:/Program Files (x86)/Windows Kits/10/Include/10.0.22000.0/um"
				},
				{
					"backtrace" : 5,
					"path" : "C:/Program Files (x86)/Windows Kits/10/Include/10.0.22000.0/winrt"
				},
				{
					"backtrace" : 5,
					"path" : "C:/skia"
				},
				{
					"backtrace" : 6,
					"isSystem" : true,
					"path" : "C:/skia/third_party/externals/emsdk/upstream/emscripten/system/include"
				}
			],
			"language" : "CXX",
			"sourceIndexes" : 
			[
				0,
				1,
				2,
				3,
				4,
				5,
				6,
				7,
				8,
				9,
				10,
				11,
				12,
				13,
				14,
				15,
				16,
				17,
				18,
				19,
				20,
				21,
				22,
				23,
				24,
				25,
				26,
				27,
				28,
				29,
				30,
				31,
				32,
				33,
				34,
				35,
				36,
				37,
				38,
				39,
				40,
				41,
				42,
				43,
				44,
				45,
				46,
				47,
				48,
				49,
				50,
				51,
				52,
				53,
				54,
				55,
				56,
				57,
				58,
				59,
				60,
				61,
				62,
				63,
				64,
				65,
				66,
				67,
				68,
				69,
				70,
				71,
				72,
				73,
				74,
				75,
				76,
				77,
				78,
				79,
				80,
				81,
				82
			]
		}
	],
	"dependencies" : 
	[
		{
			"id" : "hsw::@039278ea0a093c55e3e1"
		}
	],
	"id" : "pathkit::@039278ea0a093c55e3e1",
	"name" : "pathkit",
	"nameOnDisk" : "pathkit.lib",
	"paths" : 
	{
		"build" : "build",
		"source" : "C:/skia/out/config"
	},
	"sourceGroups" : 
	[
		{
			"name" : "Source Files",
			"sourceIndexes" : 
			[
				0,
				1,
				2,
				3,
				4,
				5,
				6,
				7,
				8,
				9,
				10,
				11,
				12,
				13,
				14,
				15,
				16,
				17,
				18,
				19,
				20,
				21,
				22,
				23,
				24,
				25,
				26,
				27,
				28,
				29,
				30,
				31,
				32,
				33,
				34,
				35,
				36,
				37,
				38,
				39,
				40,
				41,
				42,
				43,
				44,
				45,
				46,
				47,
				48,
				49,
				50,
				51,
				52,
				53,
				54,
				55,
				56,
				57,
				58,
				59,
				60,
				61,
				62,
				63,
				64,
				65,
				66,
				67,
				68,
				69,
				70,
				71,
				72,
				73,
				74,
				75,
				76,
				77,
				78,
				79,
				80,
				81,
				82
			]
		},
		{
			"name" : "Object Libraries",
			"sourceIndexes" : 
			[
				83
			]
		},
		{
			"name" : "Header Files",
			"sourceIndexes" : 
			[
				84,
				85,
				86,
				87,
				88,
				89,
				90,
				91,
				92,
				93,
				94,
				95,
				96,
				97,
				98,
				99,
				100,
				101,
				102,
				103,
				104,
				105,
				106,
				107,
				108,
				109
			]
		}
	],
	"sources" : 
	[
		{
			"backtrace" : 3,
			"compileGroupIndex" : 0,
			"path" : "C:/skia/src/pathops/SkAddIntersections.cpp",
			"sourceGroupIndex" : 0
		},
		{
			"backtrace" : 3,
			"compileGroupIndex" : 0,
			"path" : "C:/skia/src/pathops/SkDConicLineIntersection.cpp",
			"sourceGroupIndex" : 0
		},
		{
			"backtrace" : 3,
			"compileGroupIndex" : 0,
			"path" : "C:/skia/src/pathops/SkDCubicLineIntersection.cpp",
			"sourceGroupIndex" : 0
		},
		{
			"backtrace" : 3,
			"compileGroupIndex" : 0,
			"path" : "C:/skia/src/pathops/SkDCubicToQuads.cpp",
			"sourceGroupIndex" : 0
		},
		{
			"backtrace" : 3,
			"compileGroupIndex" : 0,
			"path" : "C:/skia/src/pathops/SkDLineIntersection.cpp",
			"sourceGroupIndex" : 0
		},
		{
			"backtrace" : 3,
			"compileGroupIndex" : 0,
			"path" : "C:/skia/src/pathops/SkDQuadLineIntersection.cpp",
			"sourceGroupIndex" : 0
		},
		{
			"backtrace" : 3,
			"compileGroupIndex" : 0,
			"path" : "C:/skia/src/pathops/SkIntersections.cpp",
			"sourceGroupIndex" : 0
		},
		{
			"backtrace" : 3,
			"compileGroupIndex" : 0,
			"path" : "C:/skia/src/pathops/SkOpAngle.cpp",
			"sourceGroupIndex" : 0
		},
		{
			"backtrace" : 3,
			"compileGroupIndex" : 0,
			"path" : "C:/skia/src/pathops/SkOpBuilder.cpp",
			"sourceGroupIndex" : 0
		},
		{
			"backtrace" : 3,
			"compileGroupIndex" : 0,
			"path" : "C:/skia/src/pathops/SkOpCoincidence.cpp",
			"sourceGroupIndex" : 0
		},
		{
			"backtrace" : 3,
			"compileGroupIndex" : 0,
			"path" : "C:/skia/src/pathops/SkOpContour.cpp",
			"sourceGroupIndex" : 0
		},
		{
			"backtrace" : 3,
			"compileGroupIndex" : 0,
			"path" : "C:/skia/src/pathops/SkOpCubicHull.cpp",
			"sourceGroupIndex" : 0
		},
		{
			"backtrace" : 3,
			"compileGroupIndex" : 0,
			"path" : "C:/skia/src/pathops/SkOpEdgeBuilder.cpp",
			"sourceGroupIndex" : 0
		},
		{
			"backtrace" : 3,
			"compileGroupIndex" : 0,
			"path" : "C:/skia/src/pathops/SkOpSegment.cpp",
			"sourceGroupIndex" : 0
		},
		{
			"backtrace" : 3,
			"compileGroupIndex" : 0,
			"path" : "C:/skia/src/pathops/SkOpSpan.cpp",
			"sourceGroupIndex" : 0
		},
		{
			"backtrace" : 3,
			"compileGroupIndex" : 0,
			"path" : "C:/skia/src/pathops/SkPathOpsAsWinding.cpp",
			"sourceGroupIndex" : 0
		},
		{
			"backtrace" : 3,
			"compileGroupIndex" : 0,
			"path" : "C:/skia/src/pathops/SkPathOpsCommon.cpp",
			"sourceGroupIndex" : 0
		},
		{
			"backtrace" : 3,
			"compileGroupIndex" : 0,
			"path" : "C:/skia/src/pathops/SkPathOpsConic.cpp",
			"sourceGroupIndex" : 0
		},
		{
			"backtrace" : 3,
			"compileGroupIndex" : 0,
			"path" : "C:/skia/src/pathops/SkPathOpsCubic.cpp",
			"sourceGroupIndex" : 0
		},
		{
			"backtrace" : 3,
			"compileGroupIndex" : 0,
			"path" : "C:/skia/src/pathops/SkPathOpsCurve.cpp",
			"sourceGroupIndex" : 0
		},
		{
			"backtrace" : 3,
			"compileGroupIndex" : 0,
			"path" : "C:/skia/src/pathops/SkPathOpsDebug.cpp",
			"sourceGroupIndex" : 0
		},
		{
			"backtrace" : 3,
			"compileGroupIndex" : 0,
			"path" : "C:/skia/src/pathops/SkPathOpsLine.cpp",
			"sourceGroupIndex" : 0
		},
		{
			"backtrace" : 3,
			"compileGroupIndex" : 0,
			"path" : "C:/skia/src/pathops/SkPathOpsOp.cpp",
			"sourceGroupIndex" : 0
		},
		{
			"backtrace" : 3,
			"compileGroupIndex" : 0,
			"path" : "C:/skia/src/pathops/SkPathOpsQuad.cpp",
			"sourceGroupIndex" : 0
		},
		{
			"backtrace" : 3,
			"compileGroupIndex" : 0,
			"path" : "C:/skia/src/pathops/SkPathOpsRect.cpp",
			"sourceGroupIndex" : 0
		},
		{
			"backtrace" : 3,
			"compileGroupIndex" : 0,
			"path" : "C:/skia/src/pathops/SkPathOpsSimplify.cpp",
			"sourceGroupIndex" : 0
		},
		{
			"backtrace" : 3,
			"compileGroupIndex" : 0,
			"path" : "C:/skia/src/pathops/SkPathOpsTSect.cpp",
			"sourceGroupIndex" : 0
		},
		{
			"backtrace" : 3,
			"compileGroupIndex" : 0,
			"path" : "C:/skia/src/pathops/SkPathOpsTightBounds.cpp",
			"sourceGroupIndex" : 0
		},
		{
			"backtrace" : 3,
			"compileGroupIndex" : 0,
			"path" : "C:/skia/src/pathops/SkPathOpsTypes.cpp",
			"sourceGroupIndex" : 0
		},
		{
			"backtrace" : 3,
			"compileGroupIndex" : 0,
			"path" : "C:/skia/src/pathops/SkPathOpsWinding.cpp",
			"sourceGroupIndex" : 0
		},
		{
			"backtrace" : 3,
			"compileGroupIndex" : 0,
			"path" : "C:/skia/src/pathops/SkPathWriter.cpp",
			"sourceGroupIndex" : 0
		},
		{
			"backtrace" : 3,
			"compileGroupIndex" : 0,
			"path" : "C:/skia/src/pathops/SkReduceOrder.cpp",
			"sourceGroupIndex" : 0
		},
		{
			"backtrace" : 3,
			"compileGroupIndex" : 0,
			"path" : "C:/skia/src/base/SkArenaAlloc.cpp",
			"sourceGroupIndex" : 0
		},
		{
			"backtrace" : 3,
			"compileGroupIndex" : 0,
			"path" : "C:/skia/src/base/SkBezierCurves.cpp",
			"sourceGroupIndex" : 0
		},
		{
			"backtrace" : 3,
			"compileGroupIndex" : 0,
			"path" : "C:/skia/src/base/SkContainers.cpp",
			"sourceGroupIndex" : 0
		},
		{
			"backtrace" : 3,
			"compileGroupIndex" : 0,
			"path" : "C:/skia/src/base/SkCubics.cpp",
			"sourceGroupIndex" : 0
		},
		{
			"backtrace" : 3,
			"compileGroupIndex" : 0,
			"path" : "C:/skia/src/base/SkFloatingPoint.cpp",
			"sourceGroupIndex" : 0
		},
		{
			"backtrace" : 3,
			"compileGroupIndex" : 0,
			"path" : "C:/skia/src/base/SkMalloc.cpp",
			"sourceGroupIndex" : 0
		},
		{
			"backtrace" : 3,
			"compileGroupIndex" : 0,
			"path" : "C:/skia/src/base/SkMathPriv.cpp",
			"sourceGroupIndex" : 0
		},
		{
			"backtrace" : 3,
			"compileGroupIndex" : 0,
			"path" : "C:/skia/src/base/SkQuads.cpp",
			"sourceGroupIndex" : 0
		},
		{
			"backtrace" : 3,
			"compileGroupIndex" : 0,
			"path" : "C:/skia/src/base/SkSafeMath.cpp",
			"sourceGroupIndex" : 0
		},
		{
			"backtrace" : 3,
			"compileGroupIndex" : 0,
			"path" : "C:/skia/src/base/SkSemaphore.cpp",
			"sourceGroupIndex" : 0
		},
		{
			"backtrace" : 3,
			"compileGroupIndex" : 0,
			"path" : "C:/skia/src/base/SkTDArray.cpp",
			"sourceGroupIndex" : 0
		},
		{
			"backtrace" : 3,
			"compileGroupIndex" : 0,
			"path" : "C:/skia/src/base/SkThreadID.cpp",
			"sourceGroupIndex" : 0
		},
		{
			"backtrace" : 3,
			"compileGroupIndex" : 0,
			"path" : "C:/skia/src/base/SkUTF.cpp",
			"sourceGroupIndex" : 0
		},
		{
			"backtrace" : 3,
			"compileGroupIndex" : 0,
			"path" : "C:/skia/src/base/SkUtils.cpp",
			"sourceGroupIndex" : 0
		},
		{
			"backtrace" : 3,
			"compileGroupIndex" : 0,
			"path" : "C:/skia/src/core/SkAnalyticEdge.cpp",
			"sourceGroupIndex" : 0
		},
		{
			"backtrace" : 3,
			"compileGroupIndex" : 0,
			"path" : "C:/skia/src/core/SkContourMeasure.cpp",
			"sourceGroupIndex" : 0
		},
		{
			"backtrace" : 3,
			"compileGroupIndex" : 0,
			"path" : "C:/skia/src/core/SkCubicMap.cpp",
			"sourceGroupIndex" : 0
		},
		{
			"backtrace" : 3,
			"compileGroupIndex" : 0,
			"path" : "C:/skia/src/core/SkEdge.cpp",
			"sourceGroupIndex" : 0
		},
		{
			"backtrace" : 3,
			"compileGroupIndex" : 0,
			"path" : "C:/skia/src/core/SkEdgeBuilder.cpp",
			"sourceGroupIndex" : 0
		},
		{
			"backtrace" : 3,
			"compileGroupIndex" : 0,
			"path" : "C:/skia/src/core/SkEdgeClipper.cpp",
			"sourceGroupIndex" : 0
		},
		{
			"backtrace" : 3,
			"compileGroupIndex" : 0,
			"path" : "C:/skia/src/core/SkGeometry.cpp",
			"sourceGroupIndex" : 0
		},
		{
			"backtrace" : 3,
			"compileGroupIndex" : 0,
			"path" : "C:/skia/src/core/SkIDChangeListener.cpp",
			"sourceGroupIndex" : 0
		},
		{
			"backtrace" : 3,
			"compileGroupIndex" : 0,
			"path" : "C:/skia/src/core/SkLineClipper.cpp",
			"sourceGroupIndex" : 0
		},
		{
			"backtrace" : 3,
			"compileGroupIndex" : 0,
			"path" : "C:/skia/src/core/SkMallocPixelRef.cpp",
			"sourceGroupIndex" : 0
		},
		{
			"backtrace" : 3,
			"compileGroupIndex" : 0,
			"path" : "C:/skia/src/core/SkMatrix.cpp",
			"sourceGroupIndex" : 0
		},
		{
			"backtrace" : 3,
			"compileGroupIndex" : 0,
			"path" : "C:/skia/src/core/SkOpts.cpp",
			"sourceGroupIndex" : 0
		},
		{
			"backtrace" : 3,
			"compileGroupIndex" : 0,
			"path" : "C:/skia/src/core/SkPaint.cpp",
			"sourceGroupIndex" : 0
		},
		{
			"backtrace" : 3,
			"compileGroupIndex" : 0,
			"path" : "C:/skia/src/core/SkPaintPriv.cpp",
			"sourceGroupIndex" : 0
		},
		{
			"backtrace" : 3,
			"compileGroupIndex" : 0,
			"path" : "C:/skia/src/core/SkPath.cpp",
			"sourceGroupIndex" : 0
		},
		{
			"backtrace" : 3,
			"compileGroupIndex" : 0,
			"path" : "C:/skia/src/core/SkPathBuilder.cpp",
			"sourceGroupIndex" : 0
		},
		{
			"backtrace" : 3,
			"compileGroupIndex" : 0,
			"path" : "C:/skia/src/core/SkPathEffect.cpp",
			"sourceGroupIndex" : 0
		},
		{
			"backtrace" : 3,
			"compileGroupIndex" : 0,
			"path" : "C:/skia/src/core/SkPathMeasure.cpp",
			"sourceGroupIndex" : 0
		},
		{
			"backtrace" : 3,
			"compileGroupIndex" : 0,
			"path" : "C:/skia/src/core/SkPathRef.cpp",
			"sourceGroupIndex" : 0
		},
		{
			"backtrace" : 3,
			"compileGroupIndex" : 0,
			"path" : "C:/skia/src/core/SkPathUtils.cpp",
			"sourceGroupIndex" : 0
		},
		{
			"backtrace" : 3,
			"compileGroupIndex" : 0,
			"path" : "C:/skia/src/core/SkPoint.cpp",
			"sourceGroupIndex" : 0
		},
		{
			"backtrace" : 3,
			"compileGroupIndex" : 0,
			"path" : "C:/skia/src/core/SkRRect.cpp",
			"sourceGroupIndex" : 0
		},
		{
			"backtrace" : 3,
			"compileGroupIndex" : 0,
			"path" : "C:/skia/src/core/SkReadBuffer.cpp",
			"sourceGroupIndex" : 0
		},
		{
			"backtrace" : 3,
			"compileGroupIndex" : 0,
			"path" : "C:/skia/src/core/SkRect.cpp",
			"sourceGroupIndex" : 0
		},
		{
			"backtrace" : 3,
			"compileGroupIndex" : 0,
			"path" : "C:/skia/src/core/SkStream.cpp",
			"sourceGroupIndex" : 0
		},
		{
			"backtrace" : 3,
			"compileGroupIndex" : 0,
			"path" : "C:/skia/src/core/SkString.cpp",
			"sourceGroupIndex" : 0
		},
		{
			"backtrace" : 3,
			"compileGroupIndex" : 0,
			"path" : "C:/skia/src/core/SkStringUtils.cpp",
			"sourceGroupIndex" : 0
		},
		{
			"backtrace" : 3,
			"compileGroupIndex" : 0,
			"path" : "C:/skia/src/core/SkStroke.cpp",
			"sourceGroupIndex" : 0
		},
		{
			"backtrace" : 3,
			"compileGroupIndex" : 0,
			"path" : "C:/skia/src/core/SkStrokeRec.cpp",
			"sourceGroupIndex" : 0
		},
		{
			"backtrace" : 3,
			"compileGroupIndex" : 0,
			"path" : "C:/skia/src/core/SkStrokerPriv.cpp",
			"sourceGroupIndex" : 0
		},
		{
			"backtrace" : 3,
			"compileGroupIndex" : 0,
			"path" : "C:/skia/src/effects/SkDashPathEffect.cpp",
			"sourceGroupIndex" : 0
		},
		{
			"backtrace" : 3,
			"compileGroupIndex" : 0,
			"path" : "C:/skia/src/effects/SkTrimPathEffect.cpp",
			"sourceGroupIndex" : 0
		},
		{
			"backtrace" : 3,
			"compileGroupIndex" : 0,
			"path" : "C:/skia/src/ports/SkDebug_stdio.cpp",
			"sourceGroupIndex" : 0
		},
		{
			"backtrace" : 3,
			"compileGroupIndex" : 0,
			"path" : "C:/skia/src/ports/SkMemory_malloc.cpp",
			"sourceGroupIndex" : 0
		},
		{
			"backtrace" : 3,
			"compileGroupIndex" : 0,
			"path" : "C:/skia/src/utils/SkDashPath.cpp",
			"sourceGroupIndex" : 0
		},
		{
			"backtrace" : 3,
			"compileGroupIndex" : 0,
			"path" : "C:/skia/src/utils/SkParse.cpp",
			"sourceGroupIndex" : 0
		},
		{
			"backtrace" : 3,
			"compileGroupIndex" : 0,
			"path" : "C:/skia/src/utils/SkParsePath.cpp",
			"sourceGroupIndex" : 0
		},
		{
			"backtrace" : 3,
			"isGenerated" : true,
			"path" : "cmake-build-debug/build/CMakeFiles/hsw.dir/C_/skia/src/opts/SkOpts_hsw.cpp.obj",
			"sourceGroupIndex" : 1
		},
		{
			"backtrace" : 3,
			"path" : "C:/skia/src/pathops/SkAddIntersections.h",
			"sourceGroupIndex" : 2
		},
		{
			"backtrace" : 3,
			"path" : "C:/skia/src/pathops/SkIntersectionHelper.h",
			"sourceGroupIndex" : 2
		},
		{
			"backtrace" : 3,
			"path" : "C:/skia/src/pathops/SkIntersections.h",
			"sourceGroupIndex" : 2
		},
		{
			"backtrace" : 3,
			"path" : "C:/skia/src/pathops/SkLineParameters.h",
			"sourceGroupIndex" : 2
		},
		{
			"backtrace" : 3,
			"path" : "C:/skia/src/pathops/SkOpAngle.h",
			"sourceGroupIndex" : 2
		},
		{
			"backtrace" : 3,
			"path" : "C:/skia/src/pathops/SkOpCoincidence.h",
			"sourceGroupIndex" : 2
		},
		{
			"backtrace" : 3,
			"path" : "C:/skia/src/pathops/SkOpContour.h",
			"sourceGroupIndex" : 2
		},
		{
			"backtrace" : 3,
			"path" : "C:/skia/src/pathops/SkOpEdgeBuilder.h",
			"sourceGroupIndex" : 2
		},
		{
			"backtrace" : 3,
			"path" : "C:/skia/src/pathops/SkOpSegment.h",
			"sourceGroupIndex" : 2
		},
		{
			"backtrace" : 3,
			"path" : "C:/skia/src/pathops/SkOpSpan.h",
			"sourceGroupIndex" : 2
		},
		{
			"backtrace" : 3,
			"path" : "C:/skia/src/pathops/SkPathOpsBounds.h",
			"sourceGroupIndex" : 2
		},
		{
			"backtrace" : 3,
			"path" : "C:/skia/src/pathops/SkPathOpsCommon.h",
			"sourceGroupIndex" : 2
		},
		{
			"backtrace" : 3,
			"path" : "C:/skia/src/pathops/SkPathOpsConic.h",
			"sourceGroupIndex" : 2
		},
		{
			"backtrace" : 3,
			"path" : "C:/skia/src/pathops/SkPathOpsCubic.h",
			"sourceGroupIndex" : 2
		},
		{
			"backtrace" : 3,
			"path" : "C:/skia/src/pathops/SkPathOpsCurve.h",
			"sourceGroupIndex" : 2
		},
		{
			"backtrace" : 3,
			"path" : "C:/skia/src/pathops/SkPathOpsDebug.h",
			"sourceGroupIndex" : 2
		},
		{
			"backtrace" : 3,
			"path" : "C:/skia/src/pathops/SkPathOpsLine.h",
			"sourceGroupIndex" : 2
		},
		{
			"backtrace" : 3,
			"path" : "C:/skia/src/pathops/SkPathOpsPoint.h",
			"sourceGroupIndex" : 2
		},
		{
			"backtrace" : 3,
			"path" : "C:/skia/src/pathops/SkPathOpsQuad.h",
			"sourceGroupIndex" : 2
		},
		{
			"backtrace" : 3,
			"path" : "C:/skia/src/pathops/SkPathOpsRect.h",
			"sourceGroupIndex" : 2
		},
		{
			"backtrace" : 3,
			"path" : "C:/skia/src/pathops/SkPathOpsTCurve.h",
			"sourceGroupIndex" : 2
		},
		{
			"backtrace" : 3,
			"path" : "C:/skia/src/pathops/SkPathOpsTSect.h",
			"sourceGroupIndex" : 2
		},
		{
			"backtrace" : 3,
			"path" : "C:/skia/src/pathops/SkPathOpsTypes.h",
			"sourceGroupIndex" : 2
		},
		{
			"backtrace" : 3,
			"path" : "C:/skia/src/pathops/SkPathWriter.h",
			"sourceGroupIndex" : 2
		},
		{
			"backtrace" : 3,
			"path" : "C:/skia/src/pathops/SkReduceOrder.h",
			"sourceGroupIndex" : 2
		},
		{
			"backtrace" : 3,
			"path" : "C:/skia/include/pathops/SkPathOps.h",
			"sourceGroupIndex" : 2
		}
	],
	"type" : "STATIC_LIBRARY"
}
